[
null,
{"id":1,"expanded":true,"name":"Shopping District","order":41,"parentId":0,"scrollX":816,"scrollY":814},
{"id":2,"expanded":true,"name":"Rooftop","order":42,"parentId":1,"scrollX":706.1818181818181,"scrollY":698.9090909090909},
{"id":3,"expanded":true,"name":"Downtown Plaza Base","order":1,"parentId":0,"scrollX":1666.8,"scrollY":2096.4},
{"id":4,"expanded":false,"name":"Downtown Plaza Party","order":2,"parentId":3,"scrollX":1215.6,"scrollY":1767.6},
{"id":5,"expanded":true,"name":"Opening Scene","order":67,"parentId":0,"scrollX":982.8,"scrollY":553.1999999999999},
{"id":6,"expanded":true,"name":"Cursed Subway","order":15,"parentId":0,"scrollX":982.8,"scrollY":553.1999999999999},
{"id":7,"expanded":true,"name":"Subway Car 1","order":16,"parentId":6,"scrollX":982.8,"scrollY":553.1999999999999},
{"id":8,"expanded":true,"name":"Home","order":43,"parentId":2,"scrollX":982.8,"scrollY":553.1999999999999},
{"id":9,"expanded":true,"name":"Adam's Room","order":44,"parentId":8,"scrollX":819,"scrollY":461},
{"id":10,"expanded":true,"name":"Sabrina's Room","order":46,"parentId":8,"scrollX":595.6363636363636,"scrollY":335.27272727272725},
{"id":11,"expanded":true,"name":"Eden's Room","order":47,"parentId":8,"scrollX":982.8,"scrollY":553.1999999999999},
{"id":12,"expanded":true,"name":"Bathroom","order":48,"parentId":8,"scrollX":595.6363636363636,"scrollY":335.27272727272725},
{"id":13,"expanded":true,"name":"Comic Shop","order":49,"parentId":1,"scrollX":811,"scrollY":499},
{"id":14,"expanded":true,"name":"South District","order":59,"parentId":0,"scrollX":816,"scrollY":1016},
{"id":15,"expanded":true,"name":"Back Alley","order":54,"parentId":1,"scrollX":832,"scrollY":640},
{"id":16,"expanded":true,"name":"Comic Shop Backroom","order":50,"parentId":13,"scrollX":811,"scrollY":461},
{"id":17,"expanded":true,"name":"Secret Base","order":51,"parentId":16,"scrollX":811,"scrollY":499},
{"id":18,"expanded":false,"name":"Fun House","order":3,"parentId":4,"scrollX":589.8181818181819,"scrollY":720.7272727272727},
{"id":19,"expanded":true,"name":"SubwayStation1R","order":17,"parentId":6,"scrollX":982.8,"scrollY":553.1999999999999},
{"id":20,"expanded":true,"name":"SubwayStation2R","order":18,"parentId":19,"scrollX":648.8,"scrollY":552.8},
{"id":21,"expanded":false,"name":"SubwayStation3R","order":19,"parentId":20,"scrollX":648.8,"scrollY":552.8},
{"id":22,"expanded":true,"name":"Cursed Subway F1","order":20,"parentId":6,"scrollX":2431.2,"scrollY":3249.6},
{"id":23,"expanded":true,"name":"Dark Wing's Base 1","order":60,"parentId":14,"scrollX":973.1999999999999,"scrollY":676.8},
{"id":24,"expanded":true,"name":"Flashback 1","order":68,"parentId":5,"scrollX":1092,"scrollY":614.6666666666666},
{"id":25,"expanded":false,"name":"Dark Alley","order":4,"parentId":4,"scrollX":595.6363636363636,"scrollY":335.27272727272725},
{"id":26,"expanded":true,"name":"Dark Wings Hideout","order":61,"parentId":23,"scrollX":982.8,"scrollY":553.1999999999999},
{"id":27,"expanded":true,"name":"Dark Wings Hideout (Backyard)","order":62,"parentId":26,"scrollX":819,"scrollY":461},
{"id":28,"expanded":true,"name":"Neon District","order":5,"parentId":3,"scrollX":1177.2,"scrollY":543.6},
{"id":29,"expanded":true,"name":"Gino's Store","order":6,"parentId":28,"scrollX":982.8,"scrollY":553.1999999999999},
{"id":30,"expanded":true,"name":"Flashback 2","order":69,"parentId":24,"scrollX":832,"scrollY":640},
{"id":31,"expanded":false,"name":"Robot Puzzle ","order":7,"parentId":29,"scrollX":982.8,"scrollY":553.1999999999999},
{"id":32,"expanded":false,"name":"Dark Alley 2","order":8,"parentId":28,"scrollX":819,"scrollY":461},
{"id":33,"expanded":false,"name":"Hospital","order":9,"parentId":28,"scrollX":982.8,"scrollY":553.1999999999999},
{"id":34,"expanded":false,"name":"Flashback 3","order":70,"parentId":30,"scrollX":982.8,"scrollY":553.1999999999999},
{"id":35,"expanded":false,"name":"Dark Wings Hideout (Backyard/Destroyed)","order":63,"parentId":27,"scrollX":982.8,"scrollY":553.1999999999999},
{"id":36,"expanded":true,"name":"Honor Road","order":73,"parentId":0,"scrollX":982.8,"scrollY":553.1999999999999},
{"id":37,"expanded":true,"name":"MUSEUM Entry Hall","order":74,"parentId":36,"scrollX":982.8,"scrollY":553.1999999999999},
{"id":38,"expanded":false,"name":"Library","order":75,"parentId":37,"scrollX":982.8,"scrollY":553.1999999999999},
{"id":39,"expanded":true,"name":"MUSEUM Central Hall","order":76,"parentId":37,"scrollX":982.8,"scrollY":553.1999999999999},
{"id":40,"expanded":false,"name":"Evil Rooftop","order":64,"parentId":35,"scrollX":982.8,"scrollY":553.1999999999999},
{"id":41,"expanded":true,"name":"Mobile Base","order":52,"parentId":16,"scrollX":819,"scrollY":461},
{"id":42,"expanded":false,"name":"OFFICE BUILDING","order":35,"parentId":6,"scrollX":546,"scrollY":307.3333333333333},
{"id":43,"expanded":false,"name":" CHURCH","order":36,"parentId":6,"scrollX":982.8,"scrollY":553.1999999999999},
{"id":44,"expanded":false,"name":"CHURCH ENTRYWAY","order":37,"parentId":43,"scrollX":819,"scrollY":461},
{"id":45,"expanded":false,"name":"ABANDONED SEWER TUNNEL","order":38,"parentId":6,"scrollX":982.8,"scrollY":553.1999999999999},
{"id":46,"expanded":false,"name":"SUBWAY TUNNEL","order":39,"parentId":45,"scrollX":982.8,"scrollY":553.1999999999999},
{"id":47,"expanded":false,"name":" BONEPILE ROOM","order":40,"parentId":6,"scrollX":982.8,"scrollY":553.1999999999999},
{"id":48,"expanded":true,"name":"West District","order":79,"parentId":0,"scrollX":1081.3333333333333,"scrollY":1760},
{"id":49,"expanded":true,"name":"North District","order":77,"parentId":0,"scrollX":1318.6666666666667,"scrollY":1156},
{"id":50,"expanded":false,"name":"East District","order":78,"parentId":0,"scrollX":1205.3333333333333,"scrollY":1137.3333333333333},
{"id":51,"expanded":true,"name":"Large Grocery Store","order":57,"parentId":56,"scrollX":819,"scrollY":461},
{"id":52,"expanded":false,"name":"Yousef's Office","order":66,"parentId":23,"scrollX":982.8,"scrollY":553.1999999999999},
{"id":53,"expanded":false,"name":"Limo","order":10,"parentId":28,"scrollX":982.8,"scrollY":553.1999999999999},
{"id":54,"expanded":false,"name":"Val's Office","order":65,"parentId":35,"scrollX":982.8,"scrollY":553.1999999999999},
{"id":55,"expanded":true,"name":"Credits","order":71,"parentId":5,"scrollX":819,"scrollY":461},
{"id":56,"expanded":true,"name":"Park","order":55,"parentId":1,"scrollX":832,"scrollY":640},
{"id":57,"expanded":false,"name":"LARGE SEWER DRAIN","order":56,"parentId":56,"scrollX":832,"scrollY":640},
{"id":58,"expanded":false,"name":"Credits v2","order":72,"parentId":55,"scrollX":982.8,"scrollY":553.1999999999999},
{"id":59,"expanded":true,"name":"Cursed Subway F2","order":21,"parentId":22,"scrollX":1215.6,"scrollY":3992.3999999999996},
{"id":60,"expanded":true,"name":"Room 1","order":22,"parentId":59,"scrollX":864,"scrollY":1056},
{"id":61,"expanded":true,"name":"Room 2","order":24,"parentId":59,"scrollX":973.1999999999999,"scrollY":705.6},
{"id":62,"expanded":true,"name":"Room 3","order":25,"parentId":59,"scrollX":973.6,"scrollY":842.4},
{"id":63,"expanded":true,"name":"Room 4","order":26,"parentId":59,"scrollX":869,"scrollY":978},
{"id":64,"expanded":true,"name":"Room 5","order":28,"parentId":59,"scrollX":973.1999999999999,"scrollY":1126.8},
{"id":65,"expanded":true,"name":"Room 6","order":29,"parentId":59,"scrollX":973.1999999999999,"scrollY":994.8},
{"id":66,"expanded":true,"name":"Room 7","order":30,"parentId":59,"scrollX":973.1999999999999,"scrollY":1066.8},
{"id":67,"expanded":true,"name":"Room 8","order":31,"parentId":59,"scrollX":973.1999999999999,"scrollY":1078.8},
{"id":68,"expanded":true,"name":"Room 9","order":32,"parentId":59,"scrollX":973.1999999999999,"scrollY":553.1999999999999},
{"id":69,"expanded":true,"name":"Room 10","order":33,"parentId":59,"scrollX":973.1999999999999,"scrollY":907.1999999999999},
{"id":70,"expanded":true,"name":"Boss Room","order":34,"parentId":59,"scrollX":973.3333333333334,"scrollY":894},
{"id":71,"expanded":true,"name":"Room 4 sub","order":27,"parentId":63,"scrollX":973.3333333333334,"scrollY":1096.6666666666667},
{"id":72,"expanded":false,"name":"Crystal Cave","order":23,"parentId":60,"scrollX":540.6666666666666,"scrollY":652.6666666666666},
{"id":73,"expanded":false,"name":"Charle's Apartment","order":53,"parentId":13,"scrollX":819,"scrollY":461},
{"id":74,"expanded":true,"name":"Back Alley 1","order":11,"parentId":28,"scrollX":832,"scrollY":640},
{"id":75,"expanded":true,"name":"Back Alley 2","order":12,"parentId":74,"scrollX":832,"scrollY":640},
{"id":76,"expanded":true,"name":"Back Alley 3","order":13,"parentId":75,"scrollX":832,"scrollY":640},
{"id":77,"expanded":true,"name":"Back Alley 4","order":14,"parentId":76,"scrollX":982.8,"scrollY":553.1999999999999},
{"id":78,"expanded":false,"name":"Hardware Store","order":58,"parentId":51,"scrollX":832,"scrollY":640},
{"id":79,"expanded":true,"name":"Adam's Room 2","order":45,"parentId":9,"scrollX":819,"scrollY":461}
]